fhirguard/__init__.py
fhirguard/fhirguard.py
fhirguard/metadata.py
fhirguard/tests/__init__.py
fhirguard/tests/test_fhirguard.py
fhirguard/validators/code.py
fhirguard/validators/coding.py
fhirguard/validators/validator.py
fhirguard_cli/__init__.py
fhirguard_cli/commands/metadata.py
fhirguard_cli/commands/package.py
fhirguard_cli/commands/ucum.py
fhirguard_cli/constants.py
fhirguard_cli/log.py
fhirguard_cli/main.py
fhirguard_cli/metadata/__init__.py
fhirguard_cli/metadata/discovery.py
fhirguard_cli/metadata/relationships.py
fhirguard_cli/util.py
fhirguard_core/filter.py
fhirguard_core/resources.py
fhirguard_core/tests/test_filter.py
fhirguard_core/types.py
fhirguard-0.0.1.dist-info/METADATA
fhirguard-0.0.1.dist-info/WHEEL
fhirguard-0.0.1.dist-info/entry_points.txt
fhirguard-0.0.1.dist-info/RECORD
